Metadata-Version: 1.0
Name: distributions-002
Version: 0.1
Summary: Gaussian Distribution
Home-page: UNKNOWN
Author: UNKNOWN
Author-email: UNKNOWN
License: UNKNOWN
Platform: UNKNOWN
